camely
