Metadata-Version: 2.1
Name: camely
Version: 1.0.5
Summary: Convert snake_case to camelCase
Home-page: https://yoginth.gitlab.io
Author: Yoginth
Author-email: yoginth@zoho.com
License: UNKNOWN
Project-URL: Patreon, https://www.patreon.com/yoginth
Project-URL: Source, https://gitlab.com/yoginth/camely
Platform: UNKNOWN
Classifier: Programming Language :: Python
Classifier: Natural Language :: English
Classifier: Environment :: Plugins
Classifier: Operating System :: OS Independent
Classifier: Intended Audience :: Developers
Classifier: License :: OSI Approved :: MIT License
